datahawk/__init__.py
datahawk/app.py
datahawk/datahawk.py
datahawk/data_handler/__init__.py
datahawk/data_handler/base.py
datahawk/data_handler/hf_data_handler.py
datahawk/data_handler/json_data_handler.py
datahawk/data_handler/jsonl_data_handler.py
datahawk/static/hawk-128x128.png
datahawk/static/mystyles.css
datahawk/templates/index.html
datahawk/templates/item.html
datahawk-0.0.4.dist-info/LICENSE
datahawk-0.0.4.dist-info/METADATA
datahawk-0.0.4.dist-info/WHEEL
datahawk-0.0.4.dist-info/entry_points.txt
datahawk-0.0.4.dist-info/top_level.txt
datahawk-0.0.4.dist-info/RECORD
