Metadata-Version: 2.1
Name: datahawk
Version: 0.0.4
Summary: Text data browser for visualization and analysis
Home-page: https://github.com/nihaljn/datahawk
Author: Nihal Jain
Author-email: nihal.b.jain@gmail.com
Project-URL: Bug Reports, https://github.com/nihaljn/datahawk/issues
Project-URL: Funding, https://buymeacoffee.com/nihaljn
Project-URL: Say Thanks!, https://saythanks.io/to/nihal.b.jain
Project-URL: Source, https://github.com/nihaljn/datahawk
Keywords: data visualization,research,natural language processing
Classifier: Development Status :: 3 - Alpha
Classifier: Intended Audience :: Developers
Classifier: Intended Audience :: Science/Research
Classifier: Topic :: Scientific/Engineering :: Artificial Intelligence
Classifier: Topic :: Scientific/Engineering :: Visualization
Classifier: License :: OSI Approved :: MIT License
Classifier: Programming Language :: Python :: 3
Requires-Python: >=3.8
License-File: LICENSE
Requires-Dist: flask >=2.0
Requires-Dist: datasets >=3.0
Requires-Dist: ijson >=3.3.0
